click_summarizer/__about__.py
click_summarizer/__init__.py
click_summarizer/cli.py
click_summarizer/main.py
click_summarizer-0.0.1.dist-info/METADATA
click_summarizer-0.0.1.dist-info/WHEEL
click_summarizer-0.0.1.dist-info/entry_points.txt
click_summarizer-0.0.1.dist-info/licenses/LICENSE.txt
click_summarizer-0.0.1.dist-info/RECORD
